{
  "username": "urassa_motors_company_limited",
  "full_name": "Urassa motors company limited",
  "bio": "@urassa_motors tunauza Magari aina zote\n💧Tunafanya exchange ya magari\n💧Tunakusaidia kuuza gari yako\n💧Tunakuagizia gari uipendayo\n☎️0715907041",
  "phone": "0715907041",
  "followers": 22513,
  "website": "",
  "scraped_at": "2026-06-25T12:37:34.277574+00:00",
  "posts": [
    {
      "shortcode": "C5lrbFrNXXq",
      "date": "2024-04-10T17:06:16+00:00",
      "caption": "HII NI KULIPIA NAKUONDOKA NAGARI MDAA HUO HUO ✅",
      "likes": 91,
      "images": [
        "https://eiofmomywxcsezbyzjth.supabase.co/storage/v1/object/public/listing-images/urassa_motors_company_limited/C5lrbFrNXXq_1.jpg"
      ],
      "url": "https://www.instagram.com/p/C5lrbFrNXXq/"
    },
    {
      "shortcode": "C5a4olONJHy",
      "date": "2024-04-06T12:30:04+00:00",
      "caption": "📌NJIA HII ITAKUSAIDIA KUSAVE NA KUSUBIRI USAFIRI WAKO ✅\n\n📌KWA WATEJA WANAO WEKEZA WANAELEWA JINSI WANAPATA FURAHA PINDI WANAPOMALIZA ✅\n\n📌KUWEKEZA INASAIDIA KWA WALE WWNZETU WENYE MAMBO MENGİ KWAIYO KARIBU COMPANY YETU IKO TAYARI KWA HILO ✅",
      "likes": 97,
      "images": [
        "https://eiofmomywxcsezbyzjth.supabase.co/storage/v1/object/public/listing-images/urassa_motors_company_limited/C5a4olONJHy_1.jpg"
      ],
      "url": "https://www.instagram.com/p/C5a4olONJHy/"
    },
    {
      "shortcode": "C4yfCsBtd2x",
      "date": "2024-03-21T19:56:49+00:00",
      "caption": "📌NI WAKATI WAKO WEWE AMBAE UNATAMANI KUMILIKI GARI. NA HAUNA KIASI CHOTE CHA PESA ✅\n\n📌MFANO GARI NI NI MILLION 20, UTALIPIA NUSU YAKE NI MILLION 10 TU NDANI YA SIKU TANO ZA KAZI UTAKABIDHIWA GARI YAKO ✅",
      "likes": 166,
      "images": [
        "https://eiofmomywxcsezbyzjth.supabase.co/storage/v1/object/public/listing-images/urassa_motors_company_limited/C4yfCsBtd2x_1.jpg"
      ],
      "url": "https://www.instagram.com/p/C4yfCsBtd2x/"
    },
    {
      "shortcode": "DaALmcnMgLu",
      "date": "2026-06-25T10:45:14+00:00",
      "caption": "MKOPO 💸\nCASH 💰 \nWEKEZA 💴\n\n#0715907041☎️📞",
      "likes": 1,
      "images": [
        "https://eiofmomywxcsezbyzjth.supabase.co/storage/v1/object/public/listing-images/urassa_motors_company_limited/DaALmcnMgLu_1.jpg"
      ],
      "url": "https://www.instagram.com/p/DaALmcnMgLu/"
    },
    {
      "shortcode": "DZ7uMBIDKad",
      "date": "2026-06-23T15:18:20+00:00",
      "caption": "#0715907041☎️📞",
      "likes": 1,
      "images": [
        "https://eiofmomywxcsezbyzjth.supabase.co/storage/v1/object/public/listing-images/urassa_motors_company_limited/DZ7uMBIDKad_1.jpg",
        "https://eiofmomywxcsezbyzjth.supabase.co/storage/v1/object/public/listing-images/urassa_motors_company_limited/DZ7uMBIDKad_2.jpg",
        "https://eiofmomywxcsezbyzjth.supabase.co/storage/v1/object/public/listing-images/urassa_motors_company_limited/DZ7uMBIDKad_3.jpg",
        "https://eiofmomywxcsezbyzjth.supabase.co/storage/v1/object/public/listing-images/urassa_motors_company_limited/DZ7uMBIDKad_4.jpg",
        "https://eiofmomywxcsezbyzjth.supabase.co/storage/v1/object/public/listing-images/urassa_motors_company_limited/DZ7uMBIDKad_5.jpg",
        "https://eiofmomywxcsezbyzjth.supabase.co/storage/v1/object/public/listing-images/urassa_motors_company_limited/DZ7uMBIDKad_6.jpg",
        "https://eiofmomywxcsezbyzjth.supabase.co/storage/v1/object/public/listing-images/urassa_motors_company_limited/DZ7uMBIDKad_7.jpg",
        "https://eiofmomywxcsezbyzjth.supabase.co/storage/v1/object/public/listing-images/urassa_motors_company_limited/DZ7uMBIDKad_8.jpg",
        "https://eiofmomywxcsezbyzjth.supabase.co/storage/v1/object/public/listing-images/urassa_motors_company_limited/DZ7uMBIDKad_9.jpg"
      ],
      "url": "https://www.instagram.com/p/DZ7uMBIDKad/"
    },
    {
      "shortcode": "DZ7pjq5M7uk",
      "date": "2026-06-23T14:39:07+00:00",
      "caption": "MKOPO 💸\nCASH 💰 \nWEKEZA 💴\n\n#0715907041☎️📞",
      "likes": 8,
      "images": [
        "https://eiofmomywxcsezbyzjth.supabase.co/storage/v1/object/public/listing-images/urassa_motors_company_limited/DZ7pjq5M7uk_1.jpg"
      ],
      "url": "https://www.instagram.com/p/DZ7pjq5M7uk/"
    },
    {
      "shortcode": "DZ7o9pqMxdG",
      "date": "2026-06-23T14:35:36+00:00",
      "caption": "NISSAN EXTRAILL NEW MODEL 2015 \n\nMKOPO 💸\nCASH 💰 \nWEKEZA 💴\n\n#0715907041☎️📞",
      "likes": 7,
      "images": [
        "https://eiofmomywxcsezbyzjth.supabase.co/storage/v1/object/public/listing-images/urassa_motors_company_limited/DZ7o9pqMxdG_1.jpg"
      ],
      "url": "https://www.instagram.com/p/DZ7o9pqMxdG/"
    },
    {
      "shortcode": "DZ7IQN9MbEf",
      "date": "2026-06-23T09:47:41+00:00",
      "caption": "MKOPO 💸\nCASH 💰 \nWEKEZA 💴\n\n#0715907041☎️📞",
      "likes": 6,
      "images": [
        "https://eiofmomywxcsezbyzjth.supabase.co/storage/v1/object/public/listing-images/urassa_motors_company_limited/DZ7IQN9MbEf_1.jpg"
      ],
      "url": "https://www.instagram.com/p/DZ7IQN9MbEf/"
    },
    {
      "shortcode": "DZ4uhEzshfx",
      "date": "2026-06-22T11:26:49+00:00",
      "caption": "MKOPO 💸\nCASH 💰 \nWEKEZA 💴\n\n#0715907041☎️📞",
      "likes": 9,
      "images": [
        "https://eiofmomywxcsezbyzjth.supabase.co/storage/v1/object/public/listing-images/urassa_motors_company_limited/DZ4uhEzshfx_1.jpg"
      ],
      "url": "https://www.instagram.com/p/DZ4uhEzshfx/"
    },
    {
      "shortcode": "DZrrsCEM5Zr",
      "date": "2026-06-17T09:49:22+00:00",
      "caption": "MKOPO 💸\nCASH 💰 \nWEKEZA 💴\n\n#0715907041☎️📞",
      "likes": 53,
      "images": [
        "https://eiofmomywxcsezbyzjth.supabase.co/storage/v1/object/public/listing-images/urassa_motors_company_limited/DZrrsCEM5Zr_1.jpg"
      ],
      "url": "https://www.instagram.com/p/DZrrsCEM5Zr/"
    },
    {
      "shortcode": "DZpPO3EMexa",
      "date": "2026-06-16T11:02:33+00:00",
      "caption": "MKOPO 💸\nWEKEZA 💴\nCASH 💰 \n\n#0715907041☎️📞",
      "likes": 9,
      "images": [
        "https://eiofmomywxcsezbyzjth.supabase.co/storage/v1/object/public/listing-images/urassa_motors_company_limited/DZpPO3EMexa_1.jpg"
      ],
      "url": "https://www.instagram.com/p/DZpPO3EMexa/"
    },
    {
      "shortcode": "DZpOXhwMeEo",
      "date": "2026-06-16T10:55:18+00:00",
      "caption": "MKOPO 💸\nCASH 💰 \nWEKEZA 💴\n\n#0715907041☎️📞",
      "likes": 9,
      "images": [
        "https://eiofmomywxcsezbyzjth.supabase.co/storage/v1/object/public/listing-images/urassa_motors_company_limited/DZpOXhwMeEo_1.jpg"
      ],
      "url": "https://www.instagram.com/p/DZpOXhwMeEo/"
    },
    {
      "shortcode": "DZpN_86DAgj",
      "date": "2026-06-16T10:50:44+00:00",
      "caption": "MKOPO 💸\nCASH 💰 \nWEKEZA 💴\n\n#0715907041☎️📞",
      "likes": 9,
      "images": [
        "https://eiofmomywxcsezbyzjth.supabase.co/storage/v1/object/public/listing-images/urassa_motors_company_limited/DZpN_86DAgj_1.jpg",
        "https://eiofmomywxcsezbyzjth.supabase.co/storage/v1/object/public/listing-images/urassa_motors_company_limited/DZpN_86DAgj_2.jpg"
      ],
      "url": "https://www.instagram.com/p/DZpN_86DAgj/"
    },
    {
      "shortcode": "DZpNZINDJ5T",
      "date": "2026-06-16T10:45:26+00:00",
      "caption": "#0715907041☎️📞",
      "likes": 3,
      "images": [
        "https://eiofmomywxcsezbyzjth.supabase.co/storage/v1/object/public/listing-images/urassa_motors_company_limited/DZpNZINDJ5T_1.jpg",
        "https://eiofmomywxcsezbyzjth.supabase.co/storage/v1/object/public/listing-images/urassa_motors_company_limited/DZpNZINDJ5T_2.jpg",
        "https://eiofmomywxcsezbyzjth.supabase.co/storage/v1/object/public/listing-images/urassa_motors_company_limited/DZpNZINDJ5T_3.jpg",
        "https://eiofmomywxcsezbyzjth.supabase.co/storage/v1/object/public/listing-images/urassa_motors_company_limited/DZpNZINDJ5T_4.jpg",
        "https://eiofmomywxcsezbyzjth.supabase.co/storage/v1/object/public/listing-images/urassa_motors_company_limited/DZpNZINDJ5T_5.jpg",
        "https://eiofmomywxcsezbyzjth.supabase.co/storage/v1/object/public/listing-images/urassa_motors_company_limited/DZpNZINDJ5T_6.jpg",
        "https://eiofmomywxcsezbyzjth.supabase.co/storage/v1/object/public/listing-images/urassa_motors_company_limited/DZpNZINDJ5T_7.jpg"
      ],
      "url": "https://www.instagram.com/p/DZpNZINDJ5T/"
    },
    {
      "shortcode": "DZpLuZWMxeg",
      "date": "2026-06-16T10:40:07+00:00",
      "caption": ".MKOPO 💸\nWEKEZA 💴\nCASH 💰 \n\n#0715907041☎️📞",
      "likes": 555,
      "images": [
        "https://eiofmomywxcsezbyzjth.supabase.co/storage/v1/object/public/listing-images/urassa_motors_company_limited/DZpLuZWMxeg_1.jpg"
      ],
      "url": "https://www.instagram.com/p/DZpLuZWMxeg/"
    },
    {
      "shortcode": "DZmhDxwDP6F",
      "date": "2026-06-15T09:39:34+00:00",
      "caption": "MKOPO 💸\nWEKEZA 💴\nCASH 💰",
      "likes": 6,
      "images": [
        "https://eiofmomywxcsezbyzjth.supabase.co/storage/v1/object/public/listing-images/urassa_motors_company_limited/DZmhDxwDP6F_1.jpg",
        "https://eiofmomywxcsezbyzjth.supabase.co/storage/v1/object/public/listing-images/urassa_motors_company_limited/DZmhDxwDP6F_2.jpg",
        "https://eiofmomywxcsezbyzjth.supabase.co/storage/v1/object/public/listing-images/urassa_motors_company_limited/DZmhDxwDP6F_3.jpg"
      ],
      "url": "https://www.instagram.com/p/DZmhDxwDP6F/"
    },
    {
      "shortcode": "DZeu-hHjDoR",
      "date": "2026-06-12T09:07:15+00:00",
      "caption": "MKOPO 💸\nCASH 💰 \nWEKEZA 💴\n\n#0715907041☎️📞",
      "likes": 3,
      "images": [
        "https://eiofmomywxcsezbyzjth.supabase.co/storage/v1/object/public/listing-images/urassa_motors_company_limited/DZeu-hHjDoR_1.jpg",
        "https://eiofmomywxcsezbyzjth.supabase.co/storage/v1/object/public/listing-images/urassa_motors_company_limited/DZeu-hHjDoR_2.jpg",
        "https://eiofmomywxcsezbyzjth.supabase.co/storage/v1/object/public/listing-images/urassa_motors_company_limited/DZeu-hHjDoR_3.jpg",
        "https://eiofmomywxcsezbyzjth.supabase.co/storage/v1/object/public/listing-images/urassa_motors_company_limited/DZeu-hHjDoR_4.jpg"
      ],
      "url": "https://www.instagram.com/p/DZeu-hHjDoR/"
    },
    {
      "shortcode": "DZeuuHqDHUk",
      "date": "2026-06-12T09:05:01+00:00",
      "caption": "#0715907041☎️📞",
      "likes": 2,
      "images": [
        "https://eiofmomywxcsezbyzjth.supabase.co/storage/v1/object/public/listing-images/urassa_motors_company_limited/DZeuuHqDHUk_1.jpg",
        "https://eiofmomywxcsezbyzjth.supabase.co/storage/v1/object/public/listing-images/urassa_motors_company_limited/DZeuuHqDHUk_2.jpg",
        "https://eiofmomywxcsezbyzjth.supabase.co/storage/v1/object/public/listing-images/urassa_motors_company_limited/DZeuuHqDHUk_3.jpg",
        "https://eiofmomywxcsezbyzjth.supabase.co/storage/v1/object/public/listing-images/urassa_motors_company_limited/DZeuuHqDHUk_4.jpg"
      ],
      "url": "https://www.instagram.com/p/DZeuuHqDHUk/"
    },
    {
      "shortcode": "DZczfldMTNT",
      "date": "2026-06-11T15:09:46+00:00",
      "caption": "MKOPO 💸\nCASH 💰 \nWEKEZA 💴\n\n#0715907041☎️📞",
      "likes": 4,
      "images": [
        "https://eiofmomywxcsezbyzjth.supabase.co/storage/v1/object/public/listing-images/urassa_motors_company_limited/DZczfldMTNT_1.jpg"
      ],
      "url": "https://www.instagram.com/p/DZczfldMTNT/"
    },
    {
      "shortcode": "DZcuyclsyQC",
      "date": "2026-06-11T14:28:27+00:00",
      "caption": "#0715907041☎️📞",
      "likes": 9,
      "images": [
        "https://eiofmomywxcsezbyzjth.supabase.co/storage/v1/object/public/listing-images/urassa_motors_company_limited/DZcuyclsyQC_1.jpg"
      ],
      "url": "https://www.instagram.com/p/DZcuyclsyQC/"
    },
    {
      "shortcode": "DZcti2YjHUL",
      "date": "2026-06-11T14:16:15+00:00",
      "caption": "MKOPO 💸\nWEKEZA 💴\nCASH 💰 \n\n#0715907041☎️📞",
      "likes": 4,
      "images": [
        "https://eiofmomywxcsezbyzjth.supabase.co/storage/v1/object/public/listing-images/urassa_motors_company_limited/DZcti2YjHUL_1.jpg",
        "https://eiofmomywxcsezbyzjth.supabase.co/storage/v1/object/public/listing-images/urassa_motors_company_limited/DZcti2YjHUL_2.jpg",
        "https://eiofmomywxcsezbyzjth.supabase.co/storage/v1/object/public/listing-images/urassa_motors_company_limited/DZcti2YjHUL_3.jpg"
      ],
      "url": "https://www.instagram.com/p/DZcti2YjHUL/"
    },
    {
      "shortcode": "DZcXkTLjMxB",
      "date": "2026-06-11T11:04:13+00:00",
      "caption": "Toyota ractis\nModel 2010\nEngine 1290cc\nMileage 68000km\nColor white\nSport rim\nPrice 20,500,000",
      "likes": 1,
      "images": [
        "https://eiofmomywxcsezbyzjth.supabase.co/storage/v1/object/public/listing-images/urassa_motors_company_limited/DZcXkTLjMxB_1.jpg",
        "https://eiofmomywxcsezbyzjth.supabase.co/storage/v1/object/public/listing-images/urassa_motors_company_limited/DZcXkTLjMxB_2.jpg",
        "https://eiofmomywxcsezbyzjth.supabase.co/storage/v1/object/public/listing-images/urassa_motors_company_limited/DZcXkTLjMxB_3.jpg",
        "https://eiofmomywxcsezbyzjth.supabase.co/storage/v1/object/public/listing-images/urassa_motors_company_limited/DZcXkTLjMxB_4.jpg",
        "https://eiofmomywxcsezbyzjth.supabase.co/storage/v1/object/public/listing-images/urassa_motors_company_limited/DZcXkTLjMxB_5.jpg",
        "https://eiofmomywxcsezbyzjth.supabase.co/storage/v1/object/public/listing-images/urassa_motors_company_limited/DZcXkTLjMxB_6.jpg"
      ],
      "url": "https://www.instagram.com/p/DZcXkTLjMxB/"
    },
    {
      "shortcode": "DZcXbViDI18",
      "date": "2026-06-11T11:03:00+00:00",
      "caption": "Toyota Harrier\nModel 2007\nEngine 2360cc\nColor black\nMileage 67000km\nSunroof\nElectric sterring\nElectric seats\nPrice 42,8",
      "likes": 3,
      "images": [
        "https://eiofmomywxcsezbyzjth.supabase.co/storage/v1/object/public/listing-images/urassa_motors_company_limited/DZcXbViDI18_1.jpg",
        "https://eiofmomywxcsezbyzjth.supabase.co/storage/v1/object/public/listing-images/urassa_motors_company_limited/DZcXbViDI18_2.jpg",
        "https://eiofmomywxcsezbyzjth.supabase.co/storage/v1/object/public/listing-images/urassa_motors_company_limited/DZcXbViDI18_3.jpg",
        "https://eiofmomywxcsezbyzjth.supabase.co/storage/v1/object/public/listing-images/urassa_motors_company_limited/DZcXbViDI18_4.jpg",
        "https://eiofmomywxcsezbyzjth.supabase.co/storage/v1/object/public/listing-images/urassa_motors_company_limited/DZcXbViDI18_5.jpg",
        "https://eiofmomywxcsezbyzjth.supabase.co/storage/v1/object/public/listing-images/urassa_motors_company_limited/DZcXbViDI18_6.jpg"
      ],
      "url": "https://www.instagram.com/p/DZcXbViDI18/"
    },
    {
      "shortcode": "DZSTquSMxWQ",
      "date": "2026-06-07T13:25:29+00:00",
      "caption": "MKOPO 💸\nWEKEZA 💴\nCASH 💰 \n\n#0715907041☎️📞",
      "likes": 507,
      "images": [
        "https://eiofmomywxcsezbyzjth.supabase.co/storage/v1/object/public/listing-images/urassa_motors_company_limited/DZSTquSMxWQ_1.jpg"
      ],
      "url": "https://www.instagram.com/p/DZSTquSMxWQ/"
    },
    {
      "shortcode": "DZSF2Z1jNBh",
      "date": "2026-06-07T11:17:00+00:00",
      "caption": "BEI / PRICE 55,000,000 /=\nContacts : \n\nMercedes Benz \nC class 250 AMG\nYear : 2014\nCc: 1990\nColor: white\nMileage: 64,726 Klm\nSport Rims✅\nFuel:  Petrol✅\nLeather seats✅ ( RED WINE )✅\nHeavy Sound System \nVery clean Condition\nFree registration ✅",
      "likes": 7,
      "images": [
        "https://eiofmomywxcsezbyzjth.supabase.co/storage/v1/object/public/listing-images/urassa_motors_company_limited/DZSF2Z1jNBh_1.jpg",
        "https://eiofmomywxcsezbyzjth.supabase.co/storage/v1/object/public/listing-images/urassa_motors_company_limited/DZSF2Z1jNBh_2.jpg",
        "https://eiofmomywxcsezbyzjth.supabase.co/storage/v1/object/public/listing-images/urassa_motors_company_limited/DZSF2Z1jNBh_3.jpg",
        "https://eiofmomywxcsezbyzjth.supabase.co/storage/v1/object/public/listing-images/urassa_motors_company_limited/DZSF2Z1jNBh_4.jpg",
        "https://eiofmomywxcsezbyzjth.supabase.co/storage/v1/object/public/listing-images/urassa_motors_company_limited/DZSF2Z1jNBh_5.jpg",
        "https://eiofmomywxcsezbyzjth.supabase.co/storage/v1/object/public/listing-images/urassa_motors_company_limited/DZSF2Z1jNBh_6.jpg",
        "https://eiofmomywxcsezbyzjth.supabase.co/storage/v1/object/public/listing-images/urassa_motors_company_limited/DZSF2Z1jNBh_7.jpg",
        "https://eiofmomywxcsezbyzjth.supabase.co/storage/v1/object/public/listing-images/urassa_motors_company_limited/DZSF2Z1jNBh_8.jpg",
        "https://eiofmomywxcsezbyzjth.supabase.co/storage/v1/object/public/listing-images/urassa_motors_company_limited/DZSF2Z1jNBh_9.jpg",
        "https://eiofmomywxcsezbyzjth.supabase.co/storage/v1/object/public/listing-images/urassa_motors_company_limited/DZSF2Z1jNBh_10.jpg"
      ],
      "url": "https://www.instagram.com/p/DZSF2Z1jNBh/"
    },
    {
      "shortcode": "DZNntElDFCJ",
      "date": "2026-06-05T17:36:37+00:00",
      "caption": "MKOPO 💸\nCASH 💰 \nWEKEZA 💴\n\n#0715907041☎️📞",
      "likes": 13,
      "images": [
        "https://eiofmomywxcsezbyzjth.supabase.co/storage/v1/object/public/listing-images/urassa_motors_company_limited/DZNntElDFCJ_1.jpg",
        "https://eiofmomywxcsezbyzjth.supabase.co/storage/v1/object/public/listing-images/urassa_motors_company_limited/DZNntElDFCJ_2.jpg",
        "https://eiofmomywxcsezbyzjth.supabase.co/storage/v1/object/public/listing-images/urassa_motors_company_limited/DZNntElDFCJ_3.jpg",
        "https://eiofmomywxcsezbyzjth.supabase.co/storage/v1/object/public/listing-images/urassa_motors_company_limited/DZNntElDFCJ_4.jpg",
        "https://eiofmomywxcsezbyzjth.supabase.co/storage/v1/object/public/listing-images/urassa_motors_company_limited/DZNntElDFCJ_5.jpg"
      ],
      "url": "https://www.instagram.com/p/DZNntElDFCJ/"
    },
    {
      "shortcode": "DZM5Fu6jPk4",
      "date": "2026-06-05T10:49:17+00:00",
      "caption": "MKOPO 💸\nCASH 💰 \nWEKEZA 💴\n\n#0715907041☎️📞",
      "likes": 4,
      "images": [
        "https://eiofmomywxcsezbyzjth.supabase.co/storage/v1/object/public/listing-images/urassa_motors_company_limited/DZM5Fu6jPk4_1.jpg",
        "https://eiofmomywxcsezbyzjth.supabase.co/storage/v1/object/public/listing-images/urassa_motors_company_limited/DZM5Fu6jPk4_2.jpg",
        "https://eiofmomywxcsezbyzjth.supabase.co/storage/v1/object/public/listing-images/urassa_motors_company_limited/DZM5Fu6jPk4_3.jpg",
        "https://eiofmomywxcsezbyzjth.supabase.co/storage/v1/object/public/listing-images/urassa_motors_company_limited/DZM5Fu6jPk4_4.jpg"
      ],
      "url": "https://www.instagram.com/p/DZM5Fu6jPk4/"
    },
    {
      "shortcode": "DZM4vp2DE19",
      "date": "2026-06-05T10:46:17+00:00",
      "caption": "MKOPO 💸\nCASH 💰 \nWEKEZA 💴\n\n#0715907041☎️📞",
      "likes": 4,
      "images": [
        "https://eiofmomywxcsezbyzjth.supabase.co/storage/v1/object/public/listing-images/urassa_motors_company_limited/DZM4vp2DE19_1.jpg",
        "https://eiofmomywxcsezbyzjth.supabase.co/storage/v1/object/public/listing-images/urassa_motors_company_limited/DZM4vp2DE19_2.jpg",
        "https://eiofmomywxcsezbyzjth.supabase.co/storage/v1/object/public/listing-images/urassa_motors_company_limited/DZM4vp2DE19_3.jpg"
      ],
      "url": "https://www.instagram.com/p/DZM4vp2DE19/"
    },
    {
      "shortcode": "DZM1yz3MUKX",
      "date": "2026-06-05T10:22:22+00:00",
      "caption": "NJOO @urassa_motors_company_limited TUKUKOPESHE GARI YA KAZI YAKUTEMBELEA YA SHULE WEWE TU UTAKAVYOPENDA \n\n#0715907041☎️📞",
      "likes": 15,
      "images": [
        "https://eiofmomywxcsezbyzjth.supabase.co/storage/v1/object/public/listing-images/urassa_motors_company_limited/DZM1yz3MUKX_1.jpg"
      ],
      "url": "https://www.instagram.com/p/DZM1yz3MUKX/"
    },
    {
      "shortcode": "DZM1VLyDJC-",
      "date": "2026-06-05T10:16:27+00:00",
      "caption": "MKOPO 💸\nWEKEZA 💴\nCASH 💰 \n\n#0715907041☎️📞",
      "likes": 4,
      "images": [
        "https://eiofmomywxcsezbyzjth.supabase.co/storage/v1/object/public/listing-images/urassa_motors_company_limited/DZM1VLyDJC-_1.jpg",
        "https://eiofmomywxcsezbyzjth.supabase.co/storage/v1/object/public/listing-images/urassa_motors_company_limited/DZM1VLyDJC-_2.jpg",
        "https://eiofmomywxcsezbyzjth.supabase.co/storage/v1/object/public/listing-images/urassa_motors_company_limited/DZM1VLyDJC-_3.jpg",
        "https://eiofmomywxcsezbyzjth.supabase.co/storage/v1/object/public/listing-images/urassa_motors_company_limited/DZM1VLyDJC-_4.jpg",
        "https://eiofmomywxcsezbyzjth.supabase.co/storage/v1/object/public/listing-images/urassa_motors_company_limited/DZM1VLyDJC-_5.jpg",
        "https://eiofmomywxcsezbyzjth.supabase.co/storage/v1/object/public/listing-images/urassa_motors_company_limited/DZM1VLyDJC-_6.jpg",
        "https://eiofmomywxcsezbyzjth.supabase.co/storage/v1/object/public/listing-images/urassa_motors_company_limited/DZM1VLyDJC-_7.jpg"
      ],
      "url": "https://www.instagram.com/p/DZM1VLyDJC-/"
    },
    {
      "shortcode": "DZM084Oswzz",
      "date": "2026-06-05T10:14:08+00:00",
      "caption": "MKOPO 💸\nCASH 💰 \nWEKEZA 💴\n\n#0715907041☎️📞",
      "likes": 9,
      "images": [
        "https://eiofmomywxcsezbyzjth.supabase.co/storage/v1/object/public/listing-images/urassa_motors_company_limited/DZM084Oswzz_1.jpg"
      ],
      "url": "https://www.instagram.com/p/DZM084Oswzz/"
    },
    {
      "shortcode": "DZMqOCjjFV_",
      "date": "2026-06-05T08:39:21+00:00",
      "caption": "MKOPO 💸\nCASH 💰 \nWEKEZA 💴",
      "likes": 2,
      "images": [
        "https://eiofmomywxcsezbyzjth.supabase.co/storage/v1/object/public/listing-images/urassa_motors_company_limited/DZMqOCjjFV__1.jpg",
        "https://eiofmomywxcsezbyzjth.supabase.co/storage/v1/object/public/listing-images/urassa_motors_company_limited/DZMqOCjjFV__2.jpg"
      ],
      "url": "https://www.instagram.com/p/DZMqOCjjFV_/"
    },
    {
      "shortcode": "DZMqJzEDO9W",
      "date": "2026-06-05T08:38:46+00:00",
      "caption": "MKOPO 💸\nCASH 💰 \nWEKEZA 💴",
      "likes": 3,
      "images": [
        "https://eiofmomywxcsezbyzjth.supabase.co/storage/v1/object/public/listing-images/urassa_motors_company_limited/DZMqJzEDO9W_1.jpg",
        "https://eiofmomywxcsezbyzjth.supabase.co/storage/v1/object/public/listing-images/urassa_motors_company_limited/DZMqJzEDO9W_2.jpg"
      ],
      "url": "https://www.instagram.com/p/DZMqJzEDO9W/"
    },
    {
      "shortcode": "DZMqGlDjDCU",
      "date": "2026-06-05T08:38:20+00:00",
      "caption": "MKOPO 💸\nCASH 💰 \nWEKEZA 💴",
      "likes": 4,
      "images": [
        "https://eiofmomywxcsezbyzjth.supabase.co/storage/v1/object/public/listing-images/urassa_motors_company_limited/DZMqGlDjDCU_1.jpg",
        "https://eiofmomywxcsezbyzjth.supabase.co/storage/v1/object/public/listing-images/urassa_motors_company_limited/DZMqGlDjDCU_2.jpg"
      ],
      "url": "https://www.instagram.com/p/DZMqGlDjDCU/"
    },
    {
      "shortcode": "DZHfP-tjHUn",
      "date": "2026-06-03T08:27:18+00:00",
      "caption": "LIPIA ASILIMIA 35% MPAKA 45% \n\nMKOPO 💸\nWEKEZA 💴\nCASH 💰 \n\n#0715907041☎️📞",
      "likes": 11,
      "images": [
        "https://eiofmomywxcsezbyzjth.supabase.co/storage/v1/object/public/listing-images/urassa_motors_company_limited/DZHfP-tjHUn_1.jpg",
        "https://eiofmomywxcsezbyzjth.supabase.co/storage/v1/object/public/listing-images/urassa_motors_company_limited/DZHfP-tjHUn_2.jpg",
        "https://eiofmomywxcsezbyzjth.supabase.co/storage/v1/object/public/listing-images/urassa_motors_company_limited/DZHfP-tjHUn_3.jpg",
        "https://eiofmomywxcsezbyzjth.supabase.co/storage/v1/object/public/listing-images/urassa_motors_company_limited/DZHfP-tjHUn_4.jpg",
        "https://eiofmomywxcsezbyzjth.supabase.co/storage/v1/object/public/listing-images/urassa_motors_company_limited/DZHfP-tjHUn_5.jpg"
      ],
      "url": "https://www.instagram.com/p/DZHfP-tjHUn/"
    },
    {
      "shortcode": "DZHGCW1DBF8",
      "date": "2026-06-03T04:46:59+00:00",
      "caption": "MKOPO 💸\nWEKEZA 💴\nCASH 💰 \n\n#0715907041☎️📞",
      "likes": 1,
      "images": [
        "https://eiofmomywxcsezbyzjth.supabase.co/storage/v1/object/public/listing-images/urassa_motors_company_limited/DZHGCW1DBF8_1.jpg",
        "https://eiofmomywxcsezbyzjth.supabase.co/storage/v1/object/public/listing-images/urassa_motors_company_limited/DZHGCW1DBF8_2.jpg",
        "https://eiofmomywxcsezbyzjth.supabase.co/storage/v1/object/public/listing-images/urassa_motors_company_limited/DZHGCW1DBF8_3.jpg",
        "https://eiofmomywxcsezbyzjth.supabase.co/storage/v1/object/public/listing-images/urassa_motors_company_limited/DZHGCW1DBF8_4.jpg",
        "https://eiofmomywxcsezbyzjth.supabase.co/storage/v1/object/public/listing-images/urassa_motors_company_limited/DZHGCW1DBF8_5.jpg",
        "https://eiofmomywxcsezbyzjth.supabase.co/storage/v1/object/public/listing-images/urassa_motors_company_limited/DZHGCW1DBF8_6.jpg",
        "https://eiofmomywxcsezbyzjth.supabase.co/storage/v1/object/public/listing-images/urassa_motors_company_limited/DZHGCW1DBF8_7.jpg",
        "https://eiofmomywxcsezbyzjth.supabase.co/storage/v1/object/public/listing-images/urassa_motors_company_limited/DZHGCW1DBF8_8.jpg",
        "https://eiofmomywxcsezbyzjth.supabase.co/storage/v1/object/public/listing-images/urassa_motors_company_limited/DZHGCW1DBF8_9.jpg",
        "https://eiofmomywxcsezbyzjth.supabase.co/storage/v1/object/public/listing-images/urassa_motors_company_limited/DZHGCW1DBF8_10.jpg"
      ],
      "url": "https://www.instagram.com/p/DZHGCW1DBF8/"
    },
    {
      "shortcode": "DZHFmSlsLQQ",
      "date": "2026-06-03T04:43:58+00:00",
      "caption": "MKOPO 💸\nWEKEZA 💴\nCASH 💰 \n\n#0715907041☎️📞",
      "likes": 19,
      "images": [
        "https://eiofmomywxcsezbyzjth.supabase.co/storage/v1/object/public/listing-images/urassa_motors_company_limited/DZHFmSlsLQQ_1.jpg"
      ],
      "url": "https://www.instagram.com/p/DZHFmSlsLQQ/"
    },
    {
      "shortcode": "DY9rgAFjCZo",
      "date": "2026-05-30T13:01:56+00:00",
      "caption": "MKOPO 💸\nCASH 💰 \nWEKEZA 💴\n\n#0715907041☎️📞",
      "likes": 26,
      "images": [
        "https://eiofmomywxcsezbyzjth.supabase.co/storage/v1/object/public/listing-images/urassa_motors_company_limited/DY9rgAFjCZo_1.jpg",
        "https://eiofmomywxcsezbyzjth.supabase.co/storage/v1/object/public/listing-images/urassa_motors_company_limited/DY9rgAFjCZo_2.jpg",
        "https://eiofmomywxcsezbyzjth.supabase.co/storage/v1/object/public/listing-images/urassa_motors_company_limited/DY9rgAFjCZo_3.jpg"
      ],
      "url": "https://www.instagram.com/p/DY9rgAFjCZo/"
    },
    {
      "shortcode": "DY78dNmDA5J",
      "date": "2026-05-29T20:51:37+00:00",
      "caption": "MKOPO 💸\nCASH 💰 \nWEKEZA 💴\n\n#0715907041☎️📞",
      "likes": 8,
      "images": [
        "https://eiofmomywxcsezbyzjth.supabase.co/storage/v1/object/public/listing-images/urassa_motors_company_limited/DY78dNmDA5J_1.jpg",
        "https://eiofmomywxcsezbyzjth.supabase.co/storage/v1/object/public/listing-images/urassa_motors_company_limited/DY78dNmDA5J_2.jpg",
        "https://eiofmomywxcsezbyzjth.supabase.co/storage/v1/object/public/listing-images/urassa_motors_company_limited/DY78dNmDA5J_3.jpg",
        "https://eiofmomywxcsezbyzjth.supabase.co/storage/v1/object/public/listing-images/urassa_motors_company_limited/DY78dNmDA5J_4.jpg",
        "https://eiofmomywxcsezbyzjth.supabase.co/storage/v1/object/public/listing-images/urassa_motors_company_limited/DY78dNmDA5J_5.jpg",
        "https://eiofmomywxcsezbyzjth.supabase.co/storage/v1/object/public/listing-images/urassa_motors_company_limited/DY78dNmDA5J_6.jpg"
      ],
      "url": "https://www.instagram.com/p/DY78dNmDA5J/"
    },
    {
      "shortcode": "DY7WiqxsfHD",
      "date": "2026-05-29T15:21:02+00:00",
      "caption": "CASH 💰 \nMKOPO 💸\nWEKEZA 💴\n\n#0715907041☎️📞",
      "likes": 34,
      "images": [
        "https://eiofmomywxcsezbyzjth.supabase.co/storage/v1/object/public/listing-images/urassa_motors_company_limited/DY7WiqxsfHD_1.jpg"
      ],
      "url": "https://www.instagram.com/p/DY7WiqxsfHD/"
    }
  ]
}